{"game-assets":[{"id":"3246974","link":"https://o-lobster.itch.io/another-metroidvania-asset-pack-vol-1","img_link":"https://img.itch.zone/aW1nLzIwOTQxMTk0LmdpZg==/315x250%23c/nAgDxi.gif","title":"Another Metroidvania Asset Pack Vol. 1","description":"An Collection Of Sprites, Tiles, Effects And More","author":"O_LOBSTER","sales_link":"/s/167481/free-just-grabt-it","end_date":"2025-12-01T17:12:00Z","genre":"","platforms":[]},{"id":"1399300","link":"https://miventech.itch.io/restaurant-and-house-tileset-3d-asset-pack","img_link":"https://img.itch.zone/aW1nLzgxNTUxMjQucG5n/315x250%23c/zH7uB5.png","title":"Restaurant And House TileSet 3D Asset Pack - LowPoly Voxel","description":"this is a pack of 3d resources to create restaurants and houses super easy","author":"miventech","sales_link":"/s/167718/-free-voxel-asset-pack-one-week-only","end_date":"2025-11-28T13:39:00Z","genre":"","platforms":[]},{"id":"2636957","link":"https://catterpxl.itch.io/sci-fi-exterior-32x32","img_link":"https://img.itch.zone/aW1nLzE1NzEzOTA2LnBuZw==/315x250%23c/WXv%2FPr.png","title":"Sci-Fi Interior (32x32)","description":"","author":"Catter.pxl","sales_link":"/s/167268/free-november-100-off","end_date":"2025-11-30T23:00:00Z","genre":"","platforms":[]},{"id":"3562397","link":"https://stojkea.itch.io/pixel-rpg-asset-pack","img_link":"https://img.itch.zone/aW1nLzIxMjE5MDQ1LnBuZw==/315x250%23c/EJHoAq.png","title":"Pixel RPG asset-pack","description":"32x32 Pixel art asset-pack with Tilesets, 6 different characters, animations, objects etc.","author":"Stojkea","sales_link":"/s/167578/pixel-rpg-sale","end_date":"2025-11-23T23:44:00Z","genre":"","platforms":[]},{"id":"1394972","link":"https://miventech.itch.io/modern-3d-voxel-train-car","img_link":"https://img.itch.zone/aW1nLzgxMjk0MDcucG5n/315x250%23c/W2HGC5.png","title":"Voxel  Modern Train Car, 3D Model","description":"3d model of a train car, ideal for video game decoration","author":"miventech","sales_link":"/s/167718/-free-voxel-asset-pack-one-week-only","end_date":"2025-11-28T13:39:00Z","genre":"","platforms":[]},{"id":"2175688","link":"https://miventech.itch.io/school-asset-pack-voxel","img_link":"https://img.itch.zone/aW1nLzEyODQzNTIzLnBuZw==/315x250%23c/T%2FAEwj.png","title":"Assets Pack :  School Theme Voxel","description":"Improve your video game with our school-themed assets pack! Get it now! #assetspack #video games #school","author":"miventech","sales_link":"/s/167718/-free-voxel-asset-pack-one-week-only","end_date":"2025-11-28T13:39:00Z","genre":"","platforms":[]},{"id":"2245075","link":"https://miventech.itch.io/industries-and-electricity-asset-pack","img_link":"https://img.itch.zone/aW1nLzEzMzAyMTEwLnBuZw==/315x250%23c/t0d0Ml.png","title":"Industries \u0026 Electricity Asset Pack","description":"Improve your video game with our Industries assets pack! Get it now! #assetspack #video games #Industries","author":"miventech","sales_link":"/s/167718/-free-voxel-asset-pack-one-week-only","end_date":"2025-11-28T13:39:00Z","genre":"","platforms":[]},{"id":"2188420","link":"https://miventech.itch.io/voxel-weapon-pack","img_link":"https://img.itch.zone/aW1nLzEyOTI0NTk1LnBuZw==/315x250%23c/5B1JJ0.png","title":"Voxel Weapon Asset Pack 3D","description":"Bring your game to life with a voxel-style 3D weapon asset pack! These 3D models of weapons in voxel format.","author":"miventech","sales_link":"/s/167718/-free-voxel-asset-pack-one-week-only","end_date":"2025-11-28T13:39:00Z","genre":"","platforms":[]},{"id":"2394136","link":"https://miventech.itch.io/weapon-melee-pack-3d-model-psx-lowpoly","img_link":"https://img.itch.zone/aW1nLzE0MTcxNTA1LmdpZg==/315x250%23c/jYpMFA.gif","title":"Weapon Melee Pack 3D Model  PSX - LowPoly","description":"Pack  Weapon Melee Pack with PSX - LowPoly","author":"miventech","sales_link":"/s/167718/-free-voxel-asset-pack-one-week-only","end_date":"2025-11-28T13:39:00Z","genre":"","platforms":[]},{"id":"3986195","link":"https://pacificles.itch.io/pomodoro","img_link":"https://img.itch.zone/aW1nLzIzNzc0ODE0LnBuZw==/315x250%23c/5ZCfw4.png","title":"🍅Pomodoro Timer animation","description":"Pomodoro timer animation","author":"pacificles","sales_link":"/s/167334/free-tomatoes","end_date":"2025-12-02T19:00:00Z","genre":"","platforms":[]}],"books":[],"comics":[],"tools":[],"games":[],"physical-games":[],"soundtracks":[],"game-mods":[],"misc":[]}